{
  "preRequisites:11": [
    70
  ],
  "properties:10": {
    "betterquesting:10": {
      "desc:8": "Canning Machine allows you to make Batterys.",
      "icon:10": {
        "Count:3": 1,
        "Damage:2": 170,
        "id:8": "gregtech:machine"
      },
      "name:8": "Canning Machine"
    }
  },
  "questID:3": 72,
  "tasks:9": {
    "0:10": {
      "index:3": 1,
      "requiredItems:9": {
        "0:10": {
          "Count:3": 1,
          "Damage:2": 170,
          "id:8": "gregtech:machine"
        }
      },
      "taskID:8": "bq_standard:retrieval"
    }
  }
}