{
  "preRequisites:11": [
    65
  ],
  "properties:10": {
    "betterquesting:10": {
      "desc:8": "Fun jokes aside the Resistor is a crafting component used to make the Electronic Circuit.",
      "icon:10": {
        "Count:3": 1,
        "Damage:2": 519,
        "id:8": "gregtech:meta_item_1"
      },
      "name:8": "Stop Resisting, get it?"
    }
  },
  "questID:3": 62,
  "rewards:9": {
    "0:10": {
      "index:3": 0,
      "rewardID:8": "bq_standard:item",
      "rewards:9": {
        "0:10": {
          "Count:3": 4,
          "id:8": "minecraft:paper"
        }
      }
    }
  },
  "tasks:9": {
    "0:10": {
      "index:3": 0,
      "requiredItems:9": {
        "0:10": {
          "Count:3": 2,
          "Damage:2": 519,
          "id:8": "gregtech:meta_item_1"
        }
      },
      "taskID:8": "bq_standard:retrieval"
    }
  }
}